{"ongoing_trials": {}, "hyperparameters": {"space": [{"class_name": "Int", "config": {"name": "dense_width", "default": null, "conditions": [], "min_value": 20, "max_value": 50, "step": 2, "sampling": "linear"}}, {"class_name": "Int", "config": {"name": "depth", "default": null, "conditions": [], "min_value": 6, "max_value": 12, "step": 2, "sampling": "linear"}}, {"class_name": "Choice", "config": {"name": "dense_act_fn", "default": "tanh", "conditions": [], "values": ["tanh", "sigmoid"], "ordered": false}}, {"class_name": "Float", "config": {"name": "reg_param", "default": 1e-11, "conditions": [], "min_value": 1e-11, "max_value": 0.001224, "step": null, "sampling": "log"}}, {"class_name": "Choice", "config": {"name": "dense_kernel", "default": "glorot_normal", "conditions": [], "values": ["glorot_normal", "glorot_uniform", "he_normal", "he_uniform", "random_normal", "random_uniform"], "ordered": false}}, {"class_name": "Choice", "config": {"name": "dense_bias", "default": "zeros", "conditions": [], "values": ["zeros", "random_uniform"], "ordered": false}}, {"class_name": "Choice", "config": {"name": "learning_rate", "default": 0.01, "conditions": [], "values": [0.01, 0.001, 0.0001], "ordered": true}}], "values": {"dense_width": 20, "depth": 6, "dense_act_fn": "tanh", "reg_param": 1e-11, "dense_kernel": "glorot_normal", "dense_bias": "zeros", "learning_rate": 0.01}}, "start_order": ["0000", "0001", "0002", "0003", "0004", "0005", "0006", "0007", "0008", "0009"], "end_order": ["0000", "0001", "0002", "0003", "0004", "0005", "0006", "0007", "0008", "0009"], "run_times": {"0000": 1, "0001": 1, "0002": 1, "0003": 1, "0004": 1, "0005": 1, "0006": 1, "0007": 1, "0008": 1, "0009": 1}, "retry_queue": [], "seed": 4723, "seed_state": 4779, "tried_so_far": ["4f4ba7b310cb091b821394697b81e2e6", "46d7cb594766e70ca414738764bcb73f", "53bb8cd7df49772907f77277dc3d5752", "59bbbfbe14a5c692974a1c6511d3b770", "a50dd5a8f30a7c50d4c72b596e7e283a", "c7de9d415492a9eff17ddeb5a8edc43d", "b922c4a4e3cc555437f26e61717b5af8", "8b8d273e6e3a1c633dbd14d2a6bed755", "5573bfa90a50872e29d014817b35d354", "64731be3f0de048efbdb0e78c0eee78b"], "id_to_hash": {"0000": "4f4ba7b310cb091b821394697b81e2e6", "0001": "53bb8cd7df49772907f77277dc3d5752", "0002": "c7de9d415492a9eff17ddeb5a8edc43d", "0003": "46d7cb594766e70ca414738764bcb73f", "0004": "59bbbfbe14a5c692974a1c6511d3b770", "0005": "64731be3f0de048efbdb0e78c0eee78b", "0006": "a50dd5a8f30a7c50d4c72b596e7e283a", "0007": "8b8d273e6e3a1c633dbd14d2a6bed755", "0008": "b922c4a4e3cc555437f26e61717b5af8", "0009": "5573bfa90a50872e29d014817b35d354"}, "display": {"search_start": "2024-02-24T16:50:53.500374", "trial_start": {"0000": "2024-02-24T16:50:53.500374", "0001": "2024-02-24T17:09:23.306636", "0002": "2024-02-24T17:27:52.649427", "0003": "2024-02-24T17:46:22.882524", "0004": "2024-02-24T18:04:41.196170", "0005": "2024-02-24T18:23:08.857151", "0006": "2024-02-24T18:53:31.765609", "0007": "2024-02-24T19:26:11.798890", "0008": "2024-02-24T20:19:10.686722", "0009": "2024-02-24T21:12:30.461135"}, "trial_number": {"0000": 1, "0001": 2, "0002": 3, "0003": 4, "0004": 5, "0005": 6, "0006": 7, "0007": 8, "0008": 9, "0009": 10}}, "hyperband_iterations": 1, "max_epochs": 8, "min_epochs": 1, "factor": 3, "brackets": [{"bracket_num": 0, "rounds": [[{"past_id": null, "id": "0007"}, {"past_id": null, "id": "0008"}, {"past_id": null, "id": "0009"}]]}], "current_bracket": 0, "current_iteration": 0}